drf_keycloak_auth/__init__.py
drf_keycloak_auth/apps.py
drf_keycloak_auth/authentication.py
drf_keycloak_auth/keycloak.py
drf_keycloak_auth/models.py
drf_keycloak_auth/permissions.py
drf_keycloak_auth/settings.py
drf_keycloak_auth/urls.py
drf_keycloak_auth/utils.py
drf_keycloak_auth/views.py
drf_keycloak_auth/clients/BackendRequestClient.py
drf_keycloak_auth/clients/__init__.py
drf_keycloak_auth-0.5.3.dist-info/licenses/LICENSE
drf_keycloak_auth-0.5.3.dist-info/METADATA
drf_keycloak_auth-0.5.3.dist-info/WHEEL
drf_keycloak_auth-0.5.3.dist-info/top_level.txt
drf_keycloak_auth-0.5.3.dist-info/RECORD
