Metadata-Version: 2.4
Name: drf_keycloak_auth
Version: 0.5.3
Summary: A convenience libary for authenticating users from Keycloak access tokens
Home-page: https://gitlab.com/ecocommons-australia/lib/drf-keycloak-auth
Author: EcoCommons Australia
Author-email: support@ecocommons.org.au
License: MIT
Keywords: drf,django,rest_framework,djangorestframework,authentication,python3,keycloak
Classifier: Programming Language :: Python :: 3
Classifier: License :: OSI Approved :: MIT License
Classifier: Operating System :: OS Independent
Requires-Python: >=3.10
License-File: LICENSE
Requires-Dist: djangorestframework<4,>=3.15
Requires-Dist: python-keycloak>=5.1
Requires-Dist: django>=4.1
Requires-Dist: requests_oauthlib>=2.0.0
Requires-Dist: urllib3<1.27,>=1.21.1
Requires-Dist: pyjwt>=2.6
Requires-Dist: pytz
Dynamic: author
Dynamic: author-email
Dynamic: classifier
Dynamic: description
Dynamic: description-content-type
Dynamic: home-page
Dynamic: keywords
Dynamic: license
Dynamic: license-file
Dynamic: requires-dist
Dynamic: requires-python
Dynamic: summary
